stxbaselibs/__init__.py
stxbaselibs/business_types.py
stxbaselibs/common_types.py
stxbaselibs-0.0.1.dist-info/LICENSE
stxbaselibs-0.0.1.dist-info/METADATA
stxbaselibs-0.0.1.dist-info/WHEEL
stxbaselibs-0.0.1.dist-info/top_level.txt
stxbaselibs-0.0.1.dist-info/RECORD
