Metadata-Version: 2.1
Name: stxbaselibs
Version: 0.0.1
Summary: Base libraries for other more complex projects.
Home-page: https://github.com/carloxdev/stxbaselibs
Author: Carlos A. Martínez Jiménez
Author-email: carloxdev@gmail.com
License: UNKNOWN
Project-URL: Bug Tracker, https://github.com/carloxdev/stxbaselibs/issues
Platform: UNKNOWN
Classifier: Programming Language :: Python :: 3
Classifier: License :: OSI Approved :: MIT License
Classifier: Operating System :: OS Independent
Requires-Python: >=3.6
License-File: LICENSE
